tests/__init__.py
tests/test_cli.py
tests/test_commands.py
tests/test_utils.py
tests/test_validators.py
tests/test_version.py
tests/utils.py
toil_strelka/VERSION
toil_strelka/__init__.py
toil_strelka/__main__.py
toil_strelka/cli.py
toil_strelka/commands.py
toil_strelka/exceptions.py
toil_strelka/utils.py
toil_strelka/validators.py
toil_strelka/data/README.md
toil_strelka-1.0.9.dist-info/LICENSE
toil_strelka-1.0.9.dist-info/METADATA
toil_strelka-1.0.9.dist-info/WHEEL
toil_strelka-1.0.9.dist-info/entry_points.txt
toil_strelka-1.0.9.dist-info/top_level.txt
toil_strelka-1.0.9.dist-info/RECORD
