Metadata-Version: 2.1
Name: toil-strelka
Version: 1.0.9
Summary: Toil implementation of Strelka SNV Caller
Home-page: https://github.com/papaemmelab/toil_strelka
Author: Joe Zhou, Juan Medina, Max Levine, Juan E. Arango
License: BSD
Classifier: Intended Audience :: Developers
Classifier: Intended Audience :: Science/Research
Classifier: License :: OSI Approved :: MIT License
Classifier: Natural Language :: English
Classifier: Operating System :: Unix
Classifier: Operating System :: POSIX
Classifier: Topic :: Utilities
License-File: LICENSE
Requires-Dist: toil-container (>=2.0.3)
Provides-Extra: test
Requires-Dist: coverage (>=6.2.0) ; extra == 'test'
Requires-Dist: pydocstyle (>=6.1.1) ; extra == 'test'
Requires-Dist: pytest (>=7.0.1) ; extra == 'test'
Requires-Dist: pytest-cov (>=3.0.0) ; extra == 'test'
Requires-Dist: pytest-env (>=0.6.2) ; extra == 'test'
Requires-Dist: pylint (>=2.12.2) ; extra == 'test'
Requires-Dist: tox (>=3.24.5) ; extra == 'test'
